mdtooltips.py
md_tooltips-1.3.1.dist-info/METADATA
md_tooltips-1.3.1.dist-info/WHEEL
md_tooltips-1.3.1.dist-info/top_level.txt
md_tooltips-1.3.1.dist-info/RECORD
