Metadata-Version: 2.1
Name: md-tooltips
Version: 1.3.1
Summary: UNKNOWN
Home-page: UNKNOWN
Author: UNKNOWN
Author-email: UNKNOWN
License: UNKNOWN
Platform: UNKNOWN
Requires-Dist: markdown (>=2.5)
